metapatterns/__init__.py
metapatterns/listener.py
meta_patterns-0.2.1.dist-info/LICENSE
meta_patterns-0.2.1.dist-info/METADATA
meta_patterns-0.2.1.dist-info/WHEEL
meta_patterns-0.2.1.dist-info/top_level.txt
meta_patterns-0.2.1.dist-info/RECORD
