Metadata-Version: 2.1
Name: meta-patterns
Version: 0.2.1
Summary: Design patterns for Python implemented with decorators and classes.
Home-page: https://github.com/JoeyDP/meta-patterns
Author: JoeyDP
Author-email: joeydepauw@gmail.com
License: UNKNOWN
Platform: UNKNOWN
Classifier: Programming Language :: Python :: 3
Classifier: License :: OSI Approved :: MIT License
Classifier: Operating System :: OS Independent
Requires-Python: >=3.6
